openrocket_parser/__init__.py
openrocket_parser/core.py
openrocket_parser/enums.py
openrocket_parser/units.py
openrocket_parser/components/__init__.py
openrocket_parser/components/bodytube.py
openrocket_parser/components/components.py
openrocket_parser/components/finset.py
openrocket_parser/components/motor.py
openrocket_parser/components/nosecone.py
openrocket_parser/components/rocket.py
openrocket_parser/components/stage.py
openrocket_parser/simulations/__init__.py
openrocket_parser/simulations/loader.py
openrocket_parser/simulations/simulation.py
openrocket_parser/simulations/simulation_data.py
openrocket_parser/tools/__init__.py
openrocket_parser/tools/fabricator.py
openrocket_parser/tools/flight_visualizer.py
openrocket_parser/tools/fabricator_tool/__init__.py
openrocket_parser/tools/fabricator_tool/geometry.py
openrocket_parser/tools/fabricator_tool/main_screen.py
openrocket_parser/tools/fabricator_tool/ork_parser.py
openrocket_parser/tools/fabricator_tool/settings_screen.py
openrocket_parser/tools/fabricator_tool/svg_exporter.py
openrocket_parser/tools/fabricator_tool/ui_components.py
openrocket_python_parser-0.5.1.dist-info/licenses/LICENSE
openrocket_python_parser-0.5.1.dist-info/METADATA
openrocket_python_parser-0.5.1.dist-info/WHEEL
openrocket_python_parser-0.5.1.dist-info/entry_points.txt
openrocket_python_parser-0.5.1.dist-info/top_level.txt
openrocket_python_parser-0.5.1.dist-info/RECORD
