Metadata-Version: 2.4
Name: openrocket-python-parser
Version: 0.5.1
Summary: A Python library to parse OpenRocket (.ork) XML files, including simulation data.
Author-email: "AIAA UTD Comet Rocketry, Payload" <fie150030@utdallas.edu>
Project-URL: Homepage, https://github.com/AIAA-UTD-Comet-Rocketry/openrocket-python-parser
Project-URL: Bug Tracker, https://github.com/AIAA-UTD-Comet-Rocketry/openrocket-python-parser/issues
Classifier: Programming Language :: Python :: 3
Classifier: Operating System :: OS Independent
Classifier: Topic :: Scientific/Engineering
Classifier: Development Status :: 3 - Alpha
Classifier: Topic :: Scientific/Engineering :: Visualization
Classifier: Topic :: Software Development :: Libraries :: Python Modules
Requires-Python: >=3.8
License-File: LICENSE
Requires-Dist: pandas>=1.5.0
Provides-Extra: visualizer
Requires-Dist: matplotlib; extra == "visualizer"
Provides-Extra: fabricator
Requires-Dist: svgwrite; extra == "fabricator"
Requires-Dist: kivy; extra == "fabricator"
Dynamic: license-file
